{
  "fileName": "mod.rs",
  "filePath": "governance/program/src/processor/mod.rs",
  "url": "https://github.com/solana-labs/solana-program-library/governance/program/src/processor/mod.rs",
  "summary": "The code in this file is responsible for processing various governance-related instructions in the Solana Program Library. It imports and uses multiple modules, each handling a specific governance action, such as creating a realm, depositing governing tokens, casting votes, and managing proposals.\n\nThe main function, `process_instruction`, takes three arguments: `program_id`, `accounts`, and `input`. It first attempts to deserialize the input data into a `GovernanceInstruction` enum using `try_from_slice_unchecked`. This method allows for forward compatibility, enabling newer UIs to work with older program versions.\n\nThe function then logs the instruction details, with a special case for the `InsertTransaction` instruction to avoid dumping its data into logs. Next, it matches the instruction with the corresponding processing function from the imported modules. For example, if the instruction is `CreateRealm`, it calls the `process_create_realm` function with the required arguments.\n\nHere's a brief overview of some of the supported instructions:\n\n- `CreateRealm`: Creates a new governance realm with a specified name and configuration.\n- `DepositGoverningTokens`: Deposits a specified amount of governing tokens into a governance account.\n- `WithdrawGoverningTokens`: Withdraws governing tokens from a governance account.\n- `CreateProposal`: Creates a new proposal with a given name, description, vote type, and other options.\n- `CastVote`: Casts a vote for a specific proposal.\n- `FinalizeVote`: Finalizes the voting process for a proposal.\n- `ExecuteTransaction`: Executes a transaction associated with a proposal.\n\nThese instructions, when combined, allow for the creation and management of various governance structures within the Solana ecosystem.",
  "questions": "1. **Question**: What is the purpose of the `process_instruction` function in this code?\n   **Answer**: The `process_instruction` function is the main entry point for processing instructions in the Solana program. It takes a program ID, a list of accounts, and input data, and processes the instruction based on the given input.\n\n2. **Question**: How does the code handle different types of `GovernanceInstruction`?\n   **Answer**: The code uses a match statement to handle different types of `GovernanceInstruction`. For each instruction type, it calls the corresponding process function to handle the specific instruction.\n\n3. **Question**: What is the purpose of the `try_from_slice_unchecked` function in this code?\n   **Answer**: The `try_from_slice_unchecked` function is used to deserialize the input data into a `GovernanceInstruction` instance. It is used with the `unchecked` variant to support forward compatibility of newer UI with older program versions."
}